README.md
setup.py
EODHistoricalWrapper/__init__.py
EODHistoricalWrapper.egg-info/PKG-INFO
EODHistoricalWrapper.egg-info/SOURCES.txt
EODHistoricalWrapper.egg-info/dependency_links.txt
EODHistoricalWrapper.egg-info/requires.txt
EODHistoricalWrapper.egg-info/top_level.txt